{
    "$schema": "../../../node_modules/@microsoft/sp-module-interfaces/lib/manifestSchemas/jsonSchemas/clientSideComponentManifestSchema.json",

    "id": "925b8fdb-3c50-4035-b15e-1baf4c15e994",
    "alias": "BoxButtonWebPart",
    "componentType": "WebPart",
    "version": "1.0.0",
    "manifestVersion": 2,

    "preconfiguredEntries": [{
        "groupId": "925b8fdb-3c50-4035-b15e-1baf4c15e994",
        "group": { "default": "Hub Web Parts" },
        "title": { "default": "Hub Box Button" },
        "description": { "default": "Create a large button with a colored border on it" },
        "officeFabricIconFontName": "Link",
        "properties": {
            "title": "",
            "data": [],
            "usesListMode": false,
            "advancedCamlQuery": "",
            "advancedCamlData": ""
        }
    }]
}